{
    "return_mode": "distributed",
    "routing_mode": "ppfp",
    "docker_name": "",
    "algorithm": "JGAT-MAPPO",
    "tensorboard_label": "JGAT-MAPPO",
    "max_episodes": 200,
    "max_ep_steps": 50,
    "joint_lr": 0.001,
    "gamma": 0.9,
    "k_epochs": 10,
    "eps_clip": 0.2,
    "action_std": 1.25,
    "action_std_decay_rate": 0.01,
    "min_action_std": 0.01,
    "utility_val": 0.6,
    "delay_mul": 0.4,
    "loss_rate_mul": 0.6,
    "cold_start_step": 5,
    "reserve_cuda_memory_in_gb": 0,
    "num_workers": 1,
    "topology": "Gridnet",
    "flow_rate": 0.001,
    "seed": 1,
    "ned_path": "config/ned"
}
